aind_data_migration_utils/__init__.py
aind_data_migration_utils/migrate.py
aind_data_migration_utils/utils.py
aind_data_migration_utils-0.7.0.dist-info/licenses/LICENSE
aind_data_migration_utils-0.7.0.dist-info/METADATA
aind_data_migration_utils-0.7.0.dist-info/WHEEL
aind_data_migration_utils-0.7.0.dist-info/top_level.txt
aind_data_migration_utils-0.7.0.dist-info/RECORD
